open_py/__init__.py
open_py/config.py
open_py/open_py.py
open_py/senders.py
open_py/urls.py
open_py/utils.py
tests/__init__.py
tests/const.py
tests/test.py
open_api_sdk-3.0.0.dist-info/LICENSE.txt
open_api_sdk-3.0.0.dist-info/METADATA
open_api_sdk-3.0.0.dist-info/WHEEL
open_api_sdk-3.0.0.dist-info/top_level.txt
open_api_sdk-3.0.0.dist-info/RECORD
