Metadata-Version: 2.1
Name: open-api-sdk
Version: 3.0.0
Summary: SDK library for interactions with Open Platform.
Home-page: https://github.com/OpenFuturePlatform/open-api-python-sdk
Author: OPEN Platform
Author-email: openplatform@zensoft.io
License: MIT licence
Platform: UNKNOWN
Classifier: Programming Language :: Python :: 3
Classifier: Operating System :: OS Independent
Classifier: Topic :: Software Development :: Libraries :: Python Modules
Classifier: License :: OSI Approved :: MIT License
Requires-Dist: requests
